vai_utils/__init__.py
vai_utils/data.py
vai_utils/organization.py
vai_utils/plot.py
vai_utils/data_process/__init__.py
vai_utils/data_process/load_data.py
vai_utils/data_process/validate.py
vai_utils/models/__init__.py
vai_utils/models/mixed_modes.py
vai_utils/models/timeseries/lstm.py
vai_utils/preprocess/__init__.py
vai_utils/preprocess/datetime.py
vai_utils-0.0.24.dist-info/METADATA
vai_utils-0.0.24.dist-info/WHEEL
vai_utils-0.0.24.dist-info/licenses/LICENSE
vai_utils-0.0.24.dist-info/RECORD
