Metadata-Version: 2.1
Name: vai_utils
Version: 0.0.24
Summary: VAI utils
Author-email: VirtuousAI <info@virtuousai.com>
License: Copyright (c) 2018 The Python Packaging Authority
License-File: LICENSE
Classifier: License :: OSI Approved :: MIT License
Classifier: Operating System :: OS Independent
Classifier: Programming Language :: Python :: 3
Requires-Python: >=3.4
Requires-Dist: catboost
Requires-Dist: lightgbm
Requires-Dist: matplotlib
Requires-Dist: numpy
Requires-Dist: scipy
Requires-Dist: seaborn
Requires-Dist: tensorflow
Requires-Dist: xgboost
